{
    "items": [
        {
            "id": "1",
            "articul": "1",
            "name": "Майка женская",
            "type": "Полиэтилен",
            "sostav": "Хлопок 200%",
            "plotnost": "1900",
            "sizes": [ "S (46)", "M (48)", "L (50)", "XL (52)", "XXL (54)" ],
            "colors": [
                { "orange": "images/sale-img-1.png"},
                { "blue": "images/sale-img-2.png"},
                { "purple": "images/sale-img-3.png"},
                { "green": "images/sale-img-4.png"},
                { "orange": "images/sale-item-5.png"}
            ],
            "price": {
                "1-9": "90р",
                "10-49": "15p",
                "50-249": "200p",
                "250-499": "25p",
                "500-999": "90p",
                "от 1000": "договорная"
            }
        },
        {
            "id": "2",
            "articul": "2",
            "name": "Майка мужская",
            "type": "Кулирка",
            "sostav": "Хлопок 100%",
            "plotnost": "120",
            "sizes": [ "S (46)", "M (48)", "L (50)", "XL (52)", "XXL (54)" ],
            "colors": [
                { "orange": "images/sale-img-1.png"},
                { "blue": "images/sale-img-2.png"},
                { "purple": "images/sale-img-3.png"},
                { "green": "images/sale-img-4.png"},
                { "orange": "images/sale-item-5.png"}
            ],
            "price": {
                "1-9": "95р",
                "10-49": "85p",
                "50-249": "80p",
                "250-499": "75p",
                "500-999": "70p",
                "от 1000": "договорная"
            }
        }
    ]

}